grpc_channelz/__init__.py
grpc_channelz/v1/__init__.py
grpc_channelz/v1/_async.py
grpc_channelz/v1/_servicer.py
grpc_channelz/v1/channelz.py
grpc_channelz/v1/channelz_pb2.py
grpc_channelz/v1/channelz_pb2.pyi
grpc_channelz/v1/channelz_pb2_grpc.py
grpcio_channelz-1.76.0.dist-info/LICENSE
grpcio_channelz-1.76.0.dist-info/METADATA
grpcio_channelz-1.76.0.dist-info/WHEEL
grpcio_channelz-1.76.0.dist-info/top_level.txt
grpcio_channelz-1.76.0.dist-info/RECORD
